{"Arbitrator":{"nom":"Arbitrator","CC":"38","CT":"38","F":"38","E":"38","Ag":"35","Per":"34","Int":"35","FM":"33","Soc":"30","PV":"15","PA_tete":"6","PA_bd":"6","PA_bg":"6","PA_corps":"6","PA_jd":"6","PA_jg":"6","typeA":"carapace","ES":"1","FS":"1","competences":{"gg":"ergergergergr","aeazrze":"arzeaaaaaaaaaaaaaaa","Peut relancer un test raté par round":"testtestsetsets"},"talents":["0","1"],"traits":["0","1","28","29"],"armes":{"56ba49f55c493":{"nomArme":"jhtyjtyj","groupe":"CAC","degats":"1","type":"P","pen":"1","portee":"10m1","mode":"1","AT":"1","rch":"1\/2AC","attributs":"1"}}},"56ba4ebfa030e":{"nom":"rhthrth","CC":"20","CT":"20","F":"20","E":"20","Ag":"20","Per":"20","Int":"20","FM":"20","Soc":"20","PV":"10","PA_tete":"20","PA_bd":"0","PA_bg":"0","PA_corps":"0","PA_jd":"0","PA_jg":"0","typeA":"primitif","ES":"2","FS":"1","talents":["0","1","2","157","158","189","190","191","192"],"traits":["1","2","3"],"competences":[],"armes":[]}}